pylabelme2yolo/__init__.py
pylabelme2yolo/cli.py
pylabelme2yolo/converter.py
pylabelme2yolo/utils.py
pylabelme2yolo-0.1.1.dist-info/METADATA
pylabelme2yolo-0.1.1.dist-info/WHEEL
pylabelme2yolo-0.1.1.dist-info/entry_points.txt
pylabelme2yolo-0.1.1.dist-info/top_level.txt
pylabelme2yolo-0.1.1.dist-info/RECORD
